setup.py
mleap_probability/Binomialdistribution.py
mleap_probability/Gaussiandistribution.py
mleap_probability/Generaldistribution.py
mleap_probability/__init__.py
mleap_probability.egg-info/PKG-INFO
mleap_probability.egg-info/SOURCES.txt
mleap_probability.egg-info/dependency_links.txt
mleap_probability.egg-info/not-zip-safe
mleap_probability.egg-info/top_level.txt