Metadata-Version: 1.0
Name: mleap-probability
Version: 1.2
Summary: Gaussian and Binomial distributions
Home-page: UNKNOWN
Author: ['Anna Pastwa']
Author-email: UNKNOWN
License: UNKNOWN
Platform: UNKNOWN
